Workbook

Sheet Inputs
A1: Intrinsic Value per Share (DCF Template)
A2: Blue cells are inputs. Black cells are formulas. Yellow cells are key assumptions.
A4: Company / Capital Structure
A5: Ticker (optional, for Yahoo fetch) | B5: AAPL
A6: Currency | B6: USD
A7: Cash & Equivalents | B7: 0
A8: Total Debt | B8: 0
A9: Diluted Shares Outstanding | B9: 0
A12: Cash Flow Assumptions
A13: Base Free Cash Flow (FCF0) - LTM | B13: 0
A14: Forecast Years | B14: 10
A15: Discount Rate (r) | B15: 0.1
A16: Growth Mode (Single / ByYear) | B16: Single
A17: Single Growth Rate (Years 1-10) | B17: 0.06
A19: If Growth Mode = ByYear, fill annual growth rates below (Years 1–10).
A20: Year | B20: Growth Rate
A21: 1 | B21: 0.06
A22: 2 | B22: 0.06
A23: 3 | B23: 0.06
A24: 4 | B24: 0.06
A25: 5 | B25: 0.06
A26: 6 | B26: 0.06
A27: 7 | B27: 0.06
A28: 8 | B28: 0.06
A29: 9 | B29: 0.06
A30: 10 | B30: 0.06
A33: Terminal Value Assumptions
A34: Terminal Method (Gordon / ExitMultiple) | B34: Gordon
A35: Terminal Growth Rate (g) | B35: 0.03
A36: Exit Multiple (EV/FCF) | B36: 15
A38: Margin of Safety
A39: Margin of Safety (MOS) | B39: 0.3

Sheet Model
A1: DCF Model (links from Inputs)
A3: Inputs (linked)
A4: FCF0 | B4: =Inputs!B13
A5: Forecast Years | B5: =Inputs!B14
A6: Discount Rate (r) | B6: =Inputs!B15
A7: Growth Mode | B7: =Inputs!B16
A8: Single Growth | B8: =Inputs!B17
A9: Terminal Method | B9: =Inputs!B34
A10: Terminal Growth (g) | B10: =Inputs!B35
A11: Exit Multiple | B11: =Inputs!B36
A12: Cash | B12: =Inputs!B7
A13: Debt | B13: =Inputs!B8
A14: Shares | B14: =Inputs!B9
A15: MOS | B15: =Inputs!B39
A17: Projections
A18: Metric | B18: Y1 | C18: Y2 | D18: Y3 | E18: Y4 | F18: Y5 | G18: Y6 | H18: Y7 | I18: Y8 | J18: Y9 | K18: Y10
A19: Growth Rate | B19: =IF($B$7="ByYear",Inputs!B21,$B$8) | C19: =IF($B$7="ByYear",Inputs!B22,$B$8) | D19: =IF($B$7="ByYear",Inputs!B23,$B$8) | E19: =IF($B$7="ByYear",Inputs!B24,$B$8) | F19: =IF($B$7="ByYear",Inputs!B25,$B$8) | G19: =IF($B$7="ByYear",Inputs!B26,$B$8) | H19: =IF($B$7="ByYear",Inputs!B27,$B$8) | I19: =IF($B$7="ByYear",Inputs!B28,$B$8) | J19: =IF($B$7="ByYear",Inputs!B29,$B$8) | K19: =IF($B$7="ByYear",Inputs!B30,$B$8)
A20: FCF (Projected) | B20: =$B$4*(1+B19) | C20: =B20*(1+C19) | D20: =C20*(1+D19) | E20: =D20*(1+E19) | F20: =E20*(1+F19) | G20: =F20*(1+G19) | H20: =G20*(1+H19) | I20: =H20*(1+I19) | J20: =I20*(1+J19) | K20: =J20*(1+K19)
A21: Discount Factor | B21: =1/(1+$B$6)^1 | C21: =1/(1+$B$6)^2 | D21: =1/(1+$B$6)^3 | E21: =1/(1+$B$6)^4 | F21: =1/(1+$B$6)^5 | G21: =1/(1+$B$6)^6 | H21: =1/(1+$B$6)^7 | I21: =1/(1+$B$6)^8 | J21: =1/(1+$B$6)^9 | K21: =1/(1+$B$6)^10
A22: PV of FCF | B22: =B20*B21 | C22: =C20*C21 | D22: =D20*D21 | E22: =E20*E21 | F22: =F20*F21 | G22: =G20*G21 | H22: =H20*H21 | I22: =I20*I21 | ... K22: =K20*K21
A24: PV of Cash Flows (Y1–Y10) | B24: =SUM(B22:K22)
A26: Terminal Value (at Y10) | B26: =IF($B$9="Gordon", K20*(1+$B$10)/($B$6-$B$10), K20*$B$11)
A27: PV of Terminal Value | B27: =B26*K21
A29: Enterprise Value (EV) | B29: =B24+B27
A30: Net Debt (Debt - Cash) | B30: =$B$13-$B$12
A31: Equity Value | B31: =B29-B30
A32: Intrinsic Value per Share | B32: =B31/$B$14
A33: Buy Price (MOS Applied) | B33: =B32*(1-$B$15)

Sheet UploadTemplate
A1: Manual Input Upload (Optional)
A2: Fill Column B (Value). Then copy into Inputs, or use the Python script to ingest this file.
A4: Field | B4: Value | C4: Notes
A5: Ticker | B5: AAPL | C5: Optional if using Yahoo/yfinance
A6: FCF0 (LTM) | C6: Free cash flow or owner earnings
A7: Discount Rate r | B7: 0.10 | C7: Your hurdle rate
A8: Growth Mode | B8: Single | C8: Single or ByYear
A9: Single Growth | B9: 0.06 | C9: If GrowthMode=Single
A10: Terminal Method | B10: Gordon | C10: Gordon or ExitMultiple
A11: Terminal Growth g | B11: 0.03 | C11: If TerminalMethod=Gordon
A12: Exit Multiple | B12: 15 | C12: If TerminalMethod=ExitMultiple
A13: Cash | C13: Cash & equivalents
A14: Debt | C14: Total debt
A15: Shares | C15: Diluted shares outstanding
A16: MOS | B16: 0.30 | C16: Margin of safety

Sheet README
A1: How to Use This Template
A3: 1) Go to Inputs and fill the blue cells (FCF0, discount rate, growth, terminal assumptions, cash, debt, shares, MOS). 2) If you want per-year growth, set Growth Mode to ByYear and fill Years 1–10 growth rates. 3) Model sheet computes EV, Equity Value, Intrinsic Value per Share, and MOS buy price. 4) Optional: use UploadTemplate and the provided Python script to ingest inputs automatically. Notes: - This is a simplified DCF for quick valuation discussions, not a full 3-statement model. - Sanity-check terminal assumptions and apply a margin of safety.
